progressify.py
progressify-0.4.0.dist-info/WHEEL
progressify-0.4.0.dist-info/METADATA
progressify-0.4.0.dist-info/RECORD
