Metadata-Version: 2.1
Name: progressify
Version: 0.4.0
Summary: Progress bar from an iterable, as a context manager, or decorator
License: MIT
Author: L3viathan
Author-email: git@l3vi.de
Requires-Python: >=3.7,<4.0
Classifier: License :: OSI Approved :: MIT License
Classifier: Programming Language :: Python :: 3
Classifier: Programming Language :: Python :: 3.7
Classifier: Programming Language :: Python :: 3.8
